<ns0:urlset xmlns:ns0="http://www.sitemaps.org/schemas/sitemap/0.9">
<url>
		<loc> https://geoconnex.us/ref/nat_aq/N100BSNRGB </loc>
		<lastmod> 2021-10-25 19:29:41.764851 </lastmod>
	</url><url>
		<loc> https://geoconnex.us/ref/nat_aq/N100CACSTL </loc>
		<lastmod> 2021-10-25 19:29:41.764891 </lastmod>
	</url><url>
		<loc> https://geoconnex.us/ref/nat_aq/N100CMBPLB </loc>
		<lastmod> 2021-10-25 19:29:41.764911 </lastmod>
	</url><url>
		<loc> https://geoconnex.us/ref/nat_aq/N100HGHPLN </loc>
		<lastmod> 2021-10-25 19:29:41.764929 </lastmod>
	</url><url>
		<loc> https://geoconnex.us/ref/nat_aq/N100MSRVVL </loc>
		<lastmod> 2021-10-25 19:29:41.764945 </lastmod>
	</url><url>
		<loc> https://geoconnex.us/ref/nat_aq/N100PCFNWB </loc>
		<lastmod> 2021-10-25 19:29:41.764960 </lastmod>
	</url><url>
		<loc> https://geoconnex.us/ref/nat_aq/N100PCFNWV </loc>
		<lastmod> 2021-10-25 19:29:41.764977 </lastmod>
	</url><url>
		<loc> https://geoconnex.us/ref/nat_aq/N100PCSRVR </loc>
		<lastmod> 2021-10-25 19:29:41.764994 </lastmod>
	</url><url>
		<loc> https://geoconnex.us/ref/nat_aq/N100SYMOUR </loc>
		<lastmod> 2021-10-25 19:29:41.765010 </lastmod>
	</url><url>
		<loc> https://geoconnex.us/ref/nat_aq/N100WLMLWD </loc>
		<lastmod> 2021-10-25 19:29:41.765028 </lastmod>
	</url><url>
		<loc> https://geoconnex.us/ref/nat_aq/N300ADAVMS </loc>
		<lastmod> 2021-10-25 19:29:41.765044 </lastmod>
	</url><url>
		<loc> https://geoconnex.us/ref/nat_aq/N300CNRLOK </loc>
		<lastmod> 2021-10-25 19:29:41.765059 </lastmod>
	</url><url>
		<loc> https://geoconnex.us/ref/nat_aq/N300COPLTS </loc>
		<lastmod> 2021-10-25 19:29:41.765074 </lastmod>
	</url><url>
		<loc> https://geoconnex.us/ref/nat_aq/N300ERLMZC </loc>
		<lastmod> 2021-10-25 19:29:41.765089 </lastmod>
	</url><url>
		<loc> https://geoconnex.us/ref/nat_aq/N300JCBSVL </loc>
		<lastmod> 2021-10-25 19:29:41.765104 </lastmod>
	</url><url>
		<loc> https://geoconnex.us/ref/nat_aq/N300LCRTCS </loc>
		<lastmod> 2021-10-25 19:29:41.765119 </lastmod>
	</url><url>
		<loc> https://geoconnex.us/ref/nat_aq/N300LTRTRY </loc>
		<lastmod> 2021-10-25 19:29:41.765134 </lastmod>
	</url><url>
		<loc> https://geoconnex.us/ref/nat_aq/N300MRSHLL </loc>
		<lastmod> 2021-10-25 19:29:41.765149 </lastmod>
	</url><url>
		<loc> https://geoconnex.us/ref/nat_aq/N300NYSDSN </loc>
		<lastmod> 2021-10-25 19:29:41.765164 </lastmod>
	</url><url>
		<loc> https://geoconnex.us/ref/nat_aq/N300PNSLVN </loc>
		<lastmod> 2021-10-25 19:29:41.765178 </lastmod>
	</url><url>
		<loc> https://geoconnex.us/ref/nat_aq/N300RSHSPG </loc>
		<lastmod> 2021-10-25 19:29:41.765194 </lastmod>
	</url><url>
		<loc> https://geoconnex.us/ref/nat_aq/N300UPCTCS </loc>
		<lastmod> 2021-10-25 19:29:41.765209 </lastmod>
	</url><url>
		<loc> https://geoconnex.us/ref/nat_aq/N400ABKSMP </loc>
		<lastmod> 2021-10-25 19:29:41.765224 </lastmod>
	</url><url>
		<loc> https://geoconnex.us/ref/nat_aq/N400BISCYN </loc>
		<lastmod> 2021-10-25 19:29:41.765239 </lastmod>
	</url><url>
		<loc> https://geoconnex.us/ref/nat_aq/N400BLAINE </loc>
		<lastmod> 2021-10-25 19:29:41.765254 </lastmod>
	</url><url>
		<loc> https://geoconnex.us/ref/nat_aq/N400BSNRGC </loc>
		<lastmod> 2021-10-25 19:29:41.765269 </lastmod>
	</url><url>
		<loc> https://geoconnex.us/ref/nat_aq/N400CSLHYN </loc>
		<lastmod> 2021-10-25 19:29:41.765285 </lastmod>
	</url><url>
		<loc> https://geoconnex.us/ref/nat_aq/N400KNGSHL </loc>
		<lastmod> 2021-10-25 19:29:41.765300 </lastmod>
	</url><url>
		<loc> https://geoconnex.us/ref/nat_aq/N400NYNECB </loc>
		<lastmod> 2021-10-25 19:29:41.765315 </lastmod>
	</url><url>
		<loc> https://geoconnex.us/ref/nat_aq/N400ORDVCN </loc>
		<lastmod> 2021-10-25 19:29:41.765330 </lastmod>
	</url><url>
		<loc> https://geoconnex.us/ref/nat_aq/N400PDMBRC </loc>
		<lastmod> 2021-10-25 19:29:41.765345 </lastmod>
	</url><url>
		<loc> https://geoconnex.us/ref/nat_aq/N400PDMBRX </loc>
		<lastmod> 2021-10-25 19:29:41.765360 </lastmod>
	</url><url>
		<loc> https://geoconnex.us/ref/nat_aq/N400SLRDVN </loc>
		<lastmod> 2021-10-25 19:29:41.765375 </lastmod>
	</url><url>
		<loc> https://geoconnex.us/ref/nat_aq/N400UPCRBN </loc>
		<lastmod> 2021-10-25 19:29:41.765389 </lastmod>
	</url><url>
		<loc> https://geoconnex.us/ref/nat_aq/N500MSSPPI </loc>
		<lastmod> 2021-10-25 19:29:41.765405 </lastmod>
	</url><url>
		<loc> https://geoconnex.us/ref/nat_aq/N500PLOZOC </loc>
		<lastmod> 2021-10-25 19:29:41.765420 </lastmod>
	</url><url>
		<loc> https://geoconnex.us/ref/nat_aq/N500VLYRDG </loc>
		<lastmod> 2021-10-25 19:29:41.765435 </lastmod>
	</url><url>
		<loc> https://geoconnex.us/ref/nat_aq/N600CMBPLV </loc>
		<lastmod> 2021-10-25 19:29:41.765450 </lastmod>
	</url><url>
		<loc> https://geoconnex.us/ref/nat_aq/N600HIVLCC </loc>
		<lastmod> 2021-10-25 19:29:41.765465 </lastmod>
	</url><url>
		<loc> https://geoconnex.us/ref/nat_aq/N600SKRVPB </loc>
		<lastmod> 2021-10-25 19:29:41.765480 </lastmod>
	</url><url>
		<loc> https://geoconnex.us/ref/nat_aq/N600SKRVPV </loc>
		<lastmod> 2021-10-25 19:29:41.765495 </lastmod>
	</url><url>
		<loc> https://geoconnex.us/ref/nat_aq/N600SRNVDV </loc>
		<lastmod> 2021-10-25 19:29:41.765509 </lastmod>
	</url><url>
		<loc> https://geoconnex.us/ref/nat_aq/N9999OTHER </loc>
		<lastmod> 2021-10-25 19:29:41.765525 </lastmod>
	</url><url>
		<loc> https://geoconnex.us/ref/nat_aq/S100CNRLVL </loc>
		<lastmod> 2021-10-25 19:29:41.765540 </lastmod>
	</url><url>
		<loc> https://geoconnex.us/ref/nat_aq/S100CSLLWD </loc>
		<lastmod> 2021-10-25 19:29:41.765555 </lastmod>
	</url><url>
		<loc> https://geoconnex.us/ref/nat_aq/S100MSEMBM </loc>
		<lastmod> 2021-10-25 19:29:41.765569 </lastmod>
	</url><url>
		<loc> https://geoconnex.us/ref/nat_aq/S100NATLCP </loc>
		<lastmod> 2021-10-25 19:29:41.765584 </lastmod>
	</url><url>
		<loc> https://geoconnex.us/ref/nat_aq/S100NRMTIB </loc>
		<lastmod> 2021-10-25 19:29:41.765599 </lastmod>
	</url><url>
		<loc> https://geoconnex.us/ref/nat_aq/S100PGTSND </loc>
		<lastmod> 2021-10-25 19:29:41.765614 </lastmod>
	</url><url>
		<loc> https://geoconnex.us/ref/nat_aq/S100RIOGRD </loc>
		<lastmod> 2021-10-25 19:29:41.765628 </lastmod>
	</url><url>
		<loc> https://geoconnex.us/ref/nat_aq/S100SECSLP </loc>
		<lastmod> 2021-10-25 19:29:41.765643 </lastmod>
	</url><url>
		<loc> https://geoconnex.us/ref/nat_aq/S100SURFCL </loc>
		<lastmod> 2021-10-25 19:29:41.765657 </lastmod>
	</url><url>
		<loc> https://geoconnex.us/ref/nat_aq/S100TXCLUP </loc>
		<lastmod> 2021-10-25 19:29:41.765672 </lastmod>
	</url><url>
		<loc> https://geoconnex.us/ref/nat_aq/S300CAMORD </loc>
		<lastmod> 2021-10-25 19:29:41.765687 </lastmod>
	</url><url>
		<loc> https://geoconnex.us/ref/nat_aq/S300DNVRBS </loc>
		<lastmod> 2021-10-25 19:29:41.765701 </lastmod>
	</url><url>
		<loc> https://geoconnex.us/ref/nat_aq/S400FLORDN </loc>
		<lastmod> 2021-10-25 19:29:41.765716 </lastmod>
	</url><url>
		<loc> https://geoconnex.us/ref/nat_aq/S400OZRKPL </loc>
		<lastmod> 2021-10-25 19:29:41.765731 </lastmod>
	</url><url>
		<loc> https://geoconnex.us/ref/nat_aq/S400RSWLBS </loc>
		<lastmod> 2021-10-25 19:29:41.765746 </lastmod>
	</url><url>
		<loc> https://geoconnex.us/ref/nat_aq/S500EDRTRN </loc>
		<lastmod> 2021-10-25 19:29:41.765761 </lastmod>
	</url></ns0:urlset>