<ns0:urlset xmlns:ns0="http://www.sitemaps.org/schemas/sitemap/0.9">
<url>
		<loc> https://geoconnex.us/ref/nat_aq/N100BSNRGB </loc>
		<lastmod> 2021-10-22 19:08:44.867566 </lastmod>
	</url><url>
		<loc> https://geoconnex.us/ref/nat_aq/N100CACSTL </loc>
		<lastmod> 2021-10-22 19:08:44.867613 </lastmod>
	</url><url>
		<loc> https://geoconnex.us/ref/nat_aq/N100CMBPLB </loc>
		<lastmod> 2021-10-22 19:08:44.867638 </lastmod>
	</url><url>
		<loc> https://geoconnex.us/ref/nat_aq/N100HGHPLN </loc>
		<lastmod> 2021-10-22 19:08:44.867659 </lastmod>
	</url><url>
		<loc> https://geoconnex.us/ref/nat_aq/N100MSRVVL </loc>
		<lastmod> 2021-10-22 19:08:44.867678 </lastmod>
	</url><url>
		<loc> https://geoconnex.us/ref/nat_aq/N100PCFNWB </loc>
		<lastmod> 2021-10-22 19:08:44.867698 </lastmod>
	</url><url>
		<loc> https://geoconnex.us/ref/nat_aq/N100PCFNWV </loc>
		<lastmod> 2021-10-22 19:08:44.867717 </lastmod>
	</url><url>
		<loc> https://geoconnex.us/ref/nat_aq/N100PCSRVR </loc>
		<lastmod> 2021-10-22 19:08:44.867735 </lastmod>
	</url><url>
		<loc> https://geoconnex.us/ref/nat_aq/N100SYMOUR </loc>
		<lastmod> 2021-10-22 19:08:44.867753 </lastmod>
	</url><url>
		<loc> https://geoconnex.us/ref/nat_aq/N100WLMLWD </loc>
		<lastmod> 2021-10-22 19:08:44.867771 </lastmod>
	</url><url>
		<loc> https://geoconnex.us/ref/nat_aq/N300ADAVMS </loc>
		<lastmod> 2021-10-22 19:08:44.867789 </lastmod>
	</url><url>
		<loc> https://geoconnex.us/ref/nat_aq/N300CNRLOK </loc>
		<lastmod> 2021-10-22 19:08:44.867807 </lastmod>
	</url><url>
		<loc> https://geoconnex.us/ref/nat_aq/N300COPLTS </loc>
		<lastmod> 2021-10-22 19:08:44.867825 </lastmod>
	</url><url>
		<loc> https://geoconnex.us/ref/nat_aq/N300ERLMZC </loc>
		<lastmod> 2021-10-22 19:08:44.867843 </lastmod>
	</url><url>
		<loc> https://geoconnex.us/ref/nat_aq/N300JCBSVL </loc>
		<lastmod> 2021-10-22 19:08:44.867860 </lastmod>
	</url><url>
		<loc> https://geoconnex.us/ref/nat_aq/N300LCRTCS </loc>
		<lastmod> 2021-10-22 19:08:44.867877 </lastmod>
	</url><url>
		<loc> https://geoconnex.us/ref/nat_aq/N300LTRTRY </loc>
		<lastmod> 2021-10-22 19:08:44.867895 </lastmod>
	</url><url>
		<loc> https://geoconnex.us/ref/nat_aq/N300MRSHLL </loc>
		<lastmod> 2021-10-22 19:08:44.867912 </lastmod>
	</url><url>
		<loc> https://geoconnex.us/ref/nat_aq/N300NYSDSN </loc>
		<lastmod> 2021-10-22 19:08:44.867930 </lastmod>
	</url><url>
		<loc> https://geoconnex.us/ref/nat_aq/N300PNSLVN </loc>
		<lastmod> 2021-10-22 19:08:44.867948 </lastmod>
	</url><url>
		<loc> https://geoconnex.us/ref/nat_aq/N300RSHSPG </loc>
		<lastmod> 2021-10-22 19:08:44.867965 </lastmod>
	</url><url>
		<loc> https://geoconnex.us/ref/nat_aq/N300UPCTCS </loc>
		<lastmod> 2021-10-22 19:08:44.867982 </lastmod>
	</url><url>
		<loc> https://geoconnex.us/ref/nat_aq/N400ABKSMP </loc>
		<lastmod> 2021-10-22 19:08:44.867999 </lastmod>
	</url><url>
		<loc> https://geoconnex.us/ref/nat_aq/N400BISCYN </loc>
		<lastmod> 2021-10-22 19:08:44.868017 </lastmod>
	</url><url>
		<loc> https://geoconnex.us/ref/nat_aq/N400BLAINE </loc>
		<lastmod> 2021-10-22 19:08:44.868035 </lastmod>
	</url><url>
		<loc> https://geoconnex.us/ref/nat_aq/N400BSNRGC </loc>
		<lastmod> 2021-10-22 19:08:44.868052 </lastmod>
	</url><url>
		<loc> https://geoconnex.us/ref/nat_aq/N400CSLHYN </loc>
		<lastmod> 2021-10-22 19:08:44.868070 </lastmod>
	</url><url>
		<loc> https://geoconnex.us/ref/nat_aq/N400KNGSHL </loc>
		<lastmod> 2021-10-22 19:08:44.868088 </lastmod>
	</url><url>
		<loc> https://geoconnex.us/ref/nat_aq/N400NYNECB </loc>
		<lastmod> 2021-10-22 19:08:44.868105 </lastmod>
	</url><url>
		<loc> https://geoconnex.us/ref/nat_aq/N400ORDVCN </loc>
		<lastmod> 2021-10-22 19:08:44.868135 </lastmod>
	</url><url>
		<loc> https://geoconnex.us/ref/nat_aq/N400PDMBRC </loc>
		<lastmod> 2021-10-22 19:08:44.868151 </lastmod>
	</url><url>
		<loc> https://geoconnex.us/ref/nat_aq/N400PDMBRX </loc>
		<lastmod> 2021-10-22 19:08:44.868168 </lastmod>
	</url><url>
		<loc> https://geoconnex.us/ref/nat_aq/N400SLRDVN </loc>
		<lastmod> 2021-10-22 19:08:44.868184 </lastmod>
	</url><url>
		<loc> https://geoconnex.us/ref/nat_aq/N400UPCRBN </loc>
		<lastmod> 2021-10-22 19:08:44.868201 </lastmod>
	</url><url>
		<loc> https://geoconnex.us/ref/nat_aq/N500MSSPPI </loc>
		<lastmod> 2021-10-22 19:08:44.868217 </lastmod>
	</url><url>
		<loc> https://geoconnex.us/ref/nat_aq/N500PLOZOC </loc>
		<lastmod> 2021-10-22 19:08:44.868233 </lastmod>
	</url><url>
		<loc> https://geoconnex.us/ref/nat_aq/N500VLYRDG </loc>
		<lastmod> 2021-10-22 19:08:44.868250 </lastmod>
	</url><url>
		<loc> https://geoconnex.us/ref/nat_aq/N600CMBPLV </loc>
		<lastmod> 2021-10-22 19:08:44.868268 </lastmod>
	</url><url>
		<loc> https://geoconnex.us/ref/nat_aq/N600HIVLCC </loc>
		<lastmod> 2021-10-22 19:08:44.868284 </lastmod>
	</url><url>
		<loc> https://geoconnex.us/ref/nat_aq/N600SKRVPB </loc>
		<lastmod> 2021-10-22 19:08:44.868301 </lastmod>
	</url><url>
		<loc> https://geoconnex.us/ref/nat_aq/N600SKRVPV </loc>
		<lastmod> 2021-10-22 19:08:44.868317 </lastmod>
	</url><url>
		<loc> https://geoconnex.us/ref/nat_aq/N600SRNVDV </loc>
		<lastmod> 2021-10-22 19:08:44.868333 </lastmod>
	</url><url>
		<loc> https://geoconnex.us/ref/nat_aq/N9999OTHER </loc>
		<lastmod> 2021-10-22 19:08:44.868349 </lastmod>
	</url><url>
		<loc> https://geoconnex.us/ref/nat_aq/S100CNRLVL </loc>
		<lastmod> 2021-10-22 19:08:44.868366 </lastmod>
	</url><url>
		<loc> https://geoconnex.us/ref/nat_aq/S100CSLLWD </loc>
		<lastmod> 2021-10-22 19:08:44.868382 </lastmod>
	</url><url>
		<loc> https://geoconnex.us/ref/nat_aq/S100MSEMBM </loc>
		<lastmod> 2021-10-22 19:08:44.868398 </lastmod>
	</url><url>
		<loc> https://geoconnex.us/ref/nat_aq/S100NATLCP </loc>
		<lastmod> 2021-10-22 19:08:44.868414 </lastmod>
	</url><url>
		<loc> https://geoconnex.us/ref/nat_aq/S100NRMTIB </loc>
		<lastmod> 2021-10-22 19:08:44.868430 </lastmod>
	</url><url>
		<loc> https://geoconnex.us/ref/nat_aq/S100PGTSND </loc>
		<lastmod> 2021-10-22 19:08:44.868446 </lastmod>
	</url><url>
		<loc> https://geoconnex.us/ref/nat_aq/S100RIOGRD </loc>
		<lastmod> 2021-10-22 19:08:44.868462 </lastmod>
	</url><url>
		<loc> https://geoconnex.us/ref/nat_aq/S100SECSLP </loc>
		<lastmod> 2021-10-22 19:08:44.868478 </lastmod>
	</url><url>
		<loc> https://geoconnex.us/ref/nat_aq/S100SURFCL </loc>
		<lastmod> 2021-10-22 19:08:44.868494 </lastmod>
	</url><url>
		<loc> https://geoconnex.us/ref/nat_aq/S100TXCLUP </loc>
		<lastmod> 2021-10-22 19:08:44.868510 </lastmod>
	</url><url>
		<loc> https://geoconnex.us/ref/nat_aq/S300CAMORD </loc>
		<lastmod> 2021-10-22 19:08:44.868526 </lastmod>
	</url><url>
		<loc> https://geoconnex.us/ref/nat_aq/S300DNVRBS </loc>
		<lastmod> 2021-10-22 19:08:44.868542 </lastmod>
	</url><url>
		<loc> https://geoconnex.us/ref/nat_aq/S400FLORDN </loc>
		<lastmod> 2021-10-22 19:08:44.868559 </lastmod>
	</url><url>
		<loc> https://geoconnex.us/ref/nat_aq/S400OZRKPL </loc>
		<lastmod> 2021-10-22 19:08:44.868575 </lastmod>
	</url><url>
		<loc> https://geoconnex.us/ref/nat_aq/S400RSWLBS </loc>
		<lastmod> 2021-10-22 19:08:44.868591 </lastmod>
	</url><url>
		<loc> https://geoconnex.us/ref/nat_aq/S500EDRTRN </loc>
		<lastmod> 2021-10-22 19:08:44.868607 </lastmod>
	</url></ns0:urlset>