<ns0:urlset xmlns:ns0="http://www.sitemaps.org/schemas/sitemap/0.9">
<url>
		<loc> https://geoconnex.us/cuahsi/his/ORSANCO_HAB/RCByrd </loc>
		<lastmod> 2021-10-21 19:01:42.223240 </lastmod>
	</url><url>
		<loc> https://geoconnex.us/cuahsi/his/ORSANCO_HAB/PikeIsland </loc>
		<lastmod> 2021-10-21 19:01:42.223272 </lastmod>
	</url><url>
		<loc> https://geoconnex.us/cuahsi/his/ORSANCO_HAB/Meldahl </loc>
		<lastmod> 2021-10-21 19:01:42.223293 </lastmod>
	</url><url>
		<loc> https://geoconnex.us/cuahsi/his/ORSANCO_HAB/Greenup </loc>
		<lastmod> 2021-10-21 19:01:42.223311 </lastmod>
	</url><url>
		<loc> https://geoconnex.us/cuahsi/his/ORSANCO_HAB/Sistersville </loc>
		<lastmod> 2021-10-21 19:01:42.223328 </lastmod>
	</url><url>
		<loc> https://geoconnex.us/cuahsi/his/ORSANCO_HAB/Parkersburg </loc>
		<lastmod> 2021-10-21 19:01:42.223344 </lastmod>
	</url><url>
		<loc> https://geoconnex.us/cuahsi/his/ORSANCO_HAB/Maysville </loc>
		<lastmod> 2021-10-21 19:01:42.223361 </lastmod>
	</url><url>
		<loc> https://geoconnex.us/cuahsi/his/ORSANCO_HAB/Cincinnati </loc>
		<lastmod> 2021-10-21 19:01:42.223376 </lastmod>
	</url><url>
		<loc> https://geoconnex.us/cuahsi/his/ORSANCO_HAB/Louisville </loc>
		<lastmod> 2021-10-21 19:01:42.223391 </lastmod>
	</url><url>
		<loc> https://geoconnex.us/cuahsi/his/ORSANCO_HAB/Henderson </loc>
		<lastmod> 2021-10-21 19:01:42.223407 </lastmod>
	</url></ns0:urlset>