<ns0:urlset xmlns:ns0="http://www.sitemaps.org/schemas/sitemap/0.9">
<url>
		<loc> https://geoconnex.us/cuahsi/his/Mazar_River_Project/Mazar1 </loc>
		<lastmod> 2021-10-28 18:36:18.888820 </lastmod>
	</url><url>
		<loc> https://geoconnex.us/cuahsi/his/Mazar_River_Project/La_Libertad </loc>
		<lastmod> 2021-10-28 18:36:18.888856 </lastmod>
	</url><url>
		<loc> https://geoconnex.us/cuahsi/his/Mazar_River_Project/Rio_Mazar </loc>
		<lastmod> 2021-10-28 18:36:18.888877 </lastmod>
	</url><url>
		<loc> https://geoconnex.us/cuahsi/his/Mazar_River_Project/Jennings </loc>
		<lastmod> 2021-10-28 18:36:18.888893 </lastmod>
	</url><url>
		<loc> https://geoconnex.us/cuahsi/his/Mazar_River_Project/KOH </loc>
		<lastmod> 2021-10-28 18:36:18.888909 </lastmod>
	</url><url>
		<loc> https://geoconnex.us/cuahsi/his/Mazar_River_Project/391423077150501 </loc>
		<lastmod> 2021-10-28 18:36:18.888924 </lastmod>
	</url><url>
		<loc> https://geoconnex.us/cuahsi/his/Mazar_River_Project/391426077151701 </loc>
		<lastmod> 2021-10-28 18:36:18.888939 </lastmod>
	</url><url>
		<loc> https://geoconnex.us/cuahsi/his/Mazar_River_Project/391421077153901 </loc>
		<lastmod> 2021-10-28 18:36:18.888953 </lastmod>
	</url><url>
		<loc> https://geoconnex.us/cuahsi/his/Mazar_River_Project/391433077154101 </loc>
		<lastmod> 2021-10-28 18:36:18.888968 </lastmod>
	</url><url>
		<loc> https://geoconnex.us/cuahsi/his/Mazar_River_Project/391425077160301 </loc>
		<lastmod> 2021-10-28 18:36:18.888982 </lastmod>
	</url><url>
		<loc> https://geoconnex.us/cuahsi/his/Mazar_River_Project/391420077153301 </loc>
		<lastmod> 2021-10-28 18:36:18.888996 </lastmod>
	</url><url>
		<loc> https://geoconnex.us/cuahsi/his/Mazar_River_Project/391359077152601 </loc>
		<lastmod> 2021-10-28 18:36:18.889011 </lastmod>
	</url><url>
		<loc> https://geoconnex.us/cuahsi/his/Mazar_River_Project/wq7 </loc>
		<lastmod> 2021-10-28 18:36:18.889025 </lastmod>
	</url><url>
		<loc> https://geoconnex.us/cuahsi/his/Mazar_River_Project/wq8 </loc>
		<lastmod> 2021-10-28 18:36:18.889039 </lastmod>
	</url><url>
		<loc> https://geoconnex.us/cuahsi/his/Mazar_River_Project/wq117 </loc>
		<lastmod> 2021-10-28 18:36:18.889053 </lastmod>
	</url><url>
		<loc> https://geoconnex.us/cuahsi/his/Mazar_River_Project/wq118 </loc>
		<lastmod> 2021-10-28 18:36:18.889070 </lastmod>
	</url><url>
		<loc> https://geoconnex.us/cuahsi/his/Mazar_River_Project/wq119 </loc>
		<lastmod> 2021-10-28 18:36:18.889085 </lastmod>
	</url><url>
		<loc> https://geoconnex.us/cuahsi/his/Mazar_River_Project/wq120 </loc>
		<lastmod> 2021-10-28 18:36:18.889099 </lastmod>
	</url><url>
		<loc> https://geoconnex.us/cuahsi/his/Mazar_River_Project/wq127 </loc>
		<lastmod> 2021-10-28 18:36:18.889113 </lastmod>
	</url><url>
		<loc> https://geoconnex.us/cuahsi/his/Mazar_River_Project/wq129 </loc>
		<lastmod> 2021-10-28 18:36:18.889127 </lastmod>
	</url><url>
		<loc> https://geoconnex.us/cuahsi/his/Mazar_River_Project/wq131 </loc>
		<lastmod> 2021-10-28 18:36:18.889141 </lastmod>
	</url><url>
		<loc> https://geoconnex.us/cuahsi/his/Mazar_River_Project/wq133 </loc>
		<lastmod> 2021-10-28 18:36:18.889155 </lastmod>
	</url><url>
		<loc> https://geoconnex.us/cuahsi/his/Mazar_River_Project/wq134 </loc>
		<lastmod> 2021-10-28 18:36:18.889169 </lastmod>
	</url><url>
		<loc> https://geoconnex.us/cuahsi/his/Mazar_River_Project/wq135 </loc>
		<lastmod> 2021-10-28 18:36:18.889183 </lastmod>
	</url><url>
		<loc> https://geoconnex.us/cuahsi/his/Mazar_River_Project/wq136 </loc>
		<lastmod> 2021-10-28 18:36:18.889197 </lastmod>
	</url><url>
		<loc> https://geoconnex.us/cuahsi/his/Mazar_River_Project/wq138 </loc>
		<lastmod> 2021-10-28 18:36:18.889211 </lastmod>
	</url><url>
		<loc> https://geoconnex.us/cuahsi/his/Mazar_River_Project/wq139 </loc>
		<lastmod> 2021-10-28 18:36:18.889226 </lastmod>
	</url><url>
		<loc> https://geoconnex.us/cuahsi/his/Mazar_River_Project/wq140 </loc>
		<lastmod> 2021-10-28 18:36:18.889240 </lastmod>
	</url><url>
		<loc> https://geoconnex.us/cuahsi/his/Mazar_River_Project/wq143 </loc>
		<lastmod> 2021-10-28 18:36:18.889254 </lastmod>
	</url><url>
		<loc> https://geoconnex.us/cuahsi/his/Mazar_River_Project/wq193 </loc>
		<lastmod> 2021-10-28 18:36:18.889268 </lastmod>
	</url><url>
		<loc> https://geoconnex.us/cuahsi/his/Mazar_River_Project/wq221 </loc>
		<lastmod> 2021-10-28 18:36:18.889282 </lastmod>
	</url><url>
		<loc> https://geoconnex.us/cuahsi/his/Mazar_River_Project/wq222 </loc>
		<lastmod> 2021-10-28 18:36:18.889296 </lastmod>
	</url><url>
		<loc> https://geoconnex.us/cuahsi/his/Mazar_River_Project/wq224 </loc>
		<lastmod> 2021-10-28 18:36:18.889310 </lastmod>
	</url><url>
		<loc> https://geoconnex.us/cuahsi/his/Mazar_River_Project/wq225 </loc>
		<lastmod> 2021-10-28 18:36:18.889324 </lastmod>
	</url><url>
		<loc> https://geoconnex.us/cuahsi/his/Mazar_River_Project/wq226 </loc>
		<lastmod> 2021-10-28 18:36:18.889338 </lastmod>
	</url><url>
		<loc> https://geoconnex.us/cuahsi/his/Mazar_River_Project/wq227 </loc>
		<lastmod> 2021-10-28 18:36:18.889352 </lastmod>
	</url><url>
		<loc> https://geoconnex.us/cuahsi/his/Mazar_River_Project/wq228 </loc>
		<lastmod> 2021-10-28 18:36:18.889366 </lastmod>
	</url><url>
		<loc> https://geoconnex.us/cuahsi/his/Mazar_River_Project/wq233 </loc>
		<lastmod> 2021-10-28 18:36:18.889380 </lastmod>
	</url><url>
		<loc> https://geoconnex.us/cuahsi/his/Mazar_River_Project/wq234 </loc>
		<lastmod> 2021-10-28 18:36:18.889394 </lastmod>
	</url><url>
		<loc> https://geoconnex.us/cuahsi/his/Mazar_River_Project/wq235 </loc>
		<lastmod> 2021-10-28 18:36:18.889408 </lastmod>
	</url><url>
		<loc> https://geoconnex.us/cuahsi/his/Mazar_River_Project/wq236 </loc>
		<lastmod> 2021-10-28 18:36:18.889422 </lastmod>
	</url><url>
		<loc> https://geoconnex.us/cuahsi/his/Mazar_River_Project/wq238 </loc>
		<lastmod> 2021-10-28 18:36:18.889436 </lastmod>
	</url><url>
		<loc> https://geoconnex.us/cuahsi/his/Mazar_River_Project/wq239 </loc>
		<lastmod> 2021-10-28 18:36:18.889449 </lastmod>
	</url><url>
		<loc> https://geoconnex.us/cuahsi/his/Mazar_River_Project/wq240 </loc>
		<lastmod> 2021-10-28 18:36:18.889463 </lastmod>
	</url><url>
		<loc> https://geoconnex.us/cuahsi/his/Mazar_River_Project/wq241 </loc>
		<lastmod> 2021-10-28 18:36:18.889477 </lastmod>
	</url><url>
		<loc> https://geoconnex.us/cuahsi/his/Mazar_River_Project/wq253 </loc>
		<lastmod> 2021-10-28 18:36:18.889491 </lastmod>
	</url><url>
		<loc> https://geoconnex.us/cuahsi/his/Mazar_River_Project/wq255 </loc>
		<lastmod> 2021-10-28 18:36:18.889504 </lastmod>
	</url><url>
		<loc> https://geoconnex.us/cuahsi/his/Mazar_River_Project/wq259 </loc>
		<lastmod> 2021-10-28 18:36:18.889518 </lastmod>
	</url><url>
		<loc> https://geoconnex.us/cuahsi/his/Mazar_River_Project/wq260 </loc>
		<lastmod> 2021-10-28 18:36:18.889532 </lastmod>
	</url><url>
		<loc> https://geoconnex.us/cuahsi/his/Mazar_River_Project/wq261 </loc>
		<lastmod> 2021-10-28 18:36:18.889546 </lastmod>
	</url><url>
		<loc> https://geoconnex.us/cuahsi/his/Mazar_River_Project/wq262 </loc>
		<lastmod> 2021-10-28 18:36:18.889560 </lastmod>
	</url><url>
		<loc> https://geoconnex.us/cuahsi/his/Mazar_River_Project/wq264 </loc>
		<lastmod> 2021-10-28 18:36:18.889573 </lastmod>
	</url><url>
		<loc> https://geoconnex.us/cuahsi/his/Mazar_River_Project/wq265 </loc>
		<lastmod> 2021-10-28 18:36:18.889587 </lastmod>
	</url><url>
		<loc> https://geoconnex.us/cuahsi/his/Mazar_River_Project/wq266 </loc>
		<lastmod> 2021-10-28 18:36:18.889602 </lastmod>
	</url><url>
		<loc> https://geoconnex.us/cuahsi/his/Mazar_River_Project/wq267 </loc>
		<lastmod> 2021-10-28 18:36:18.889616 </lastmod>
	</url><url>
		<loc> https://geoconnex.us/cuahsi/his/Mazar_River_Project/wq268 </loc>
		<lastmod> 2021-10-28 18:36:18.889630 </lastmod>
	</url><url>
		<loc> https://geoconnex.us/cuahsi/his/Mazar_River_Project/wq269 </loc>
		<lastmod> 2021-10-28 18:36:18.889644 </lastmod>
	</url><url>
		<loc> https://geoconnex.us/cuahsi/his/Mazar_River_Project/wq270 </loc>
		<lastmod> 2021-10-28 18:36:18.889658 </lastmod>
	</url><url>
		<loc> https://geoconnex.us/cuahsi/his/Mazar_River_Project/wq271 </loc>
		<lastmod> 2021-10-28 18:36:18.889672 </lastmod>
	</url><url>
		<loc> https://geoconnex.us/cuahsi/his/Mazar_River_Project/wq272 </loc>
		<lastmod> 2021-10-28 18:36:18.889686 </lastmod>
	</url><url>
		<loc> https://geoconnex.us/cuahsi/his/Mazar_River_Project/wq275 </loc>
		<lastmod> 2021-10-28 18:36:18.889700 </lastmod>
	</url><url>
		<loc> https://geoconnex.us/cuahsi/his/Mazar_River_Project/wq290 </loc>
		<lastmod> 2021-10-28 18:36:18.889714 </lastmod>
	</url><url>
		<loc> https://geoconnex.us/cuahsi/his/Mazar_River_Project/wq296 </loc>
		<lastmod> 2021-10-28 18:36:18.889728 </lastmod>
	</url><url>
		<loc> https://geoconnex.us/cuahsi/his/Mazar_River_Project/wq297 </loc>
		<lastmod> 2021-10-28 18:36:18.889741 </lastmod>
	</url><url>
		<loc> https://geoconnex.us/cuahsi/his/Mazar_River_Project/wq299 </loc>
		<lastmod> 2021-10-28 18:36:18.889755 </lastmod>
	</url><url>
		<loc> https://geoconnex.us/cuahsi/his/Mazar_River_Project/wq300 </loc>
		<lastmod> 2021-10-28 18:36:18.889769 </lastmod>
	</url><url>
		<loc> https://geoconnex.us/cuahsi/his/Mazar_River_Project/wq301 </loc>
		<lastmod> 2021-10-28 18:36:18.889783 </lastmod>
	</url><url>
		<loc> https://geoconnex.us/cuahsi/his/Mazar_River_Project/wq302 </loc>
		<lastmod> 2021-10-28 18:36:18.889797 </lastmod>
	</url><url>
		<loc> https://geoconnex.us/cuahsi/his/Mazar_River_Project/wq303 </loc>
		<lastmod> 2021-10-28 18:36:18.889812 </lastmod>
	</url><url>
		<loc> https://geoconnex.us/cuahsi/his/Mazar_River_Project/wq304 </loc>
		<lastmod> 2021-10-28 18:36:18.889826 </lastmod>
	</url><url>
		<loc> https://geoconnex.us/cuahsi/his/Mazar_River_Project/wq305 </loc>
		<lastmod> 2021-10-28 18:36:18.889840 </lastmod>
	</url><url>
		<loc> https://geoconnex.us/cuahsi/his/Mazar_River_Project/wq306 </loc>
		<lastmod> 2021-10-28 18:36:18.889854 </lastmod>
	</url><url>
		<loc> https://geoconnex.us/cuahsi/his/Mazar_River_Project/wq308 </loc>
		<lastmod> 2021-10-28 18:36:18.889868 </lastmod>
	</url><url>
		<loc> https://geoconnex.us/cuahsi/his/Mazar_River_Project/wq309 </loc>
		<lastmod> 2021-10-28 18:36:18.889882 </lastmod>
	</url><url>
		<loc> https://geoconnex.us/cuahsi/his/Mazar_River_Project/wq310 </loc>
		<lastmod> 2021-10-28 18:36:18.889896 </lastmod>
	</url><url>
		<loc> https://geoconnex.us/cuahsi/his/Mazar_River_Project/wq311 </loc>
		<lastmod> 2021-10-28 18:36:18.889910 </lastmod>
	</url><url>
		<loc> https://geoconnex.us/cuahsi/his/Mazar_River_Project/wq312 </loc>
		<lastmod> 2021-10-28 18:36:18.889924 </lastmod>
	</url><url>
		<loc> https://geoconnex.us/cuahsi/his/Mazar_River_Project/wq325 </loc>
		<lastmod> 2021-10-28 18:36:18.889938 </lastmod>
	</url><url>
		<loc> https://geoconnex.us/cuahsi/his/Mazar_River_Project/wq326 </loc>
		<lastmod> 2021-10-28 18:36:18.889952 </lastmod>
	</url><url>
		<loc> https://geoconnex.us/cuahsi/his/Mazar_River_Project/wq456 </loc>
		<lastmod> 2021-10-28 18:36:18.889966 </lastmod>
	</url><url>
		<loc> https://geoconnex.us/cuahsi/his/Mazar_River_Project/wq457 </loc>
		<lastmod> 2021-10-28 18:36:18.889980 </lastmod>
	</url><url>
		<loc> https://geoconnex.us/cuahsi/his/Mazar_River_Project/wq475 </loc>
		<lastmod> 2021-10-28 18:36:18.889994 </lastmod>
	</url><url>
		<loc> https://geoconnex.us/cuahsi/his/Mazar_River_Project/wq477 </loc>
		<lastmod> 2021-10-28 18:36:18.890009 </lastmod>
	</url><url>
		<loc> https://geoconnex.us/cuahsi/his/Mazar_River_Project/wq478 </loc>
		<lastmod> 2021-10-28 18:36:18.890023 </lastmod>
	</url><url>
		<loc> https://geoconnex.us/cuahsi/his/Mazar_River_Project/wq480 </loc>
		<lastmod> 2021-10-28 18:36:18.890037 </lastmod>
	</url><url>
		<loc> https://geoconnex.us/cuahsi/his/Mazar_River_Project/wq482 </loc>
		<lastmod> 2021-10-28 18:36:18.890051 </lastmod>
	</url><url>
		<loc> https://geoconnex.us/cuahsi/his/Mazar_River_Project/wq484 </loc>
		<lastmod> 2021-10-28 18:36:18.890066 </lastmod>
	</url><url>
		<loc> https://geoconnex.us/cuahsi/his/Mazar_River_Project/wq553 </loc>
		<lastmod> 2021-10-28 18:36:18.890080 </lastmod>
	</url><url>
		<loc> https://geoconnex.us/cuahsi/his/Mazar_River_Project/wq554 </loc>
		<lastmod> 2021-10-28 18:36:18.890094 </lastmod>
	</url><url>
		<loc> https://geoconnex.us/cuahsi/his/Mazar_River_Project/wq555 </loc>
		<lastmod> 2021-10-28 18:36:18.890108 </lastmod>
	</url><url>
		<loc> https://geoconnex.us/cuahsi/his/Mazar_River_Project/wq563 </loc>
		<lastmod> 2021-10-28 18:36:18.890122 </lastmod>
	</url><url>
		<loc> https://geoconnex.us/cuahsi/his/Mazar_River_Project/wq566 </loc>
		<lastmod> 2021-10-28 18:36:18.890136 </lastmod>
	</url><url>
		<loc> https://geoconnex.us/cuahsi/his/Mazar_River_Project/wq567 </loc>
		<lastmod> 2021-10-28 18:36:18.890150 </lastmod>
	</url><url>
		<loc> https://geoconnex.us/cuahsi/his/Mazar_River_Project/wq568 </loc>
		<lastmod> 2021-10-28 18:36:18.890164 </lastmod>
	</url><url>
		<loc> https://geoconnex.us/cuahsi/his/Mazar_River_Project/wq569 </loc>
		<lastmod> 2021-10-28 18:36:18.890178 </lastmod>
	</url><url>
		<loc> https://geoconnex.us/cuahsi/his/Mazar_River_Project/wq572 </loc>
		<lastmod> 2021-10-28 18:36:18.890191 </lastmod>
	</url><url>
		<loc> https://geoconnex.us/cuahsi/his/Mazar_River_Project/wq586 </loc>
		<lastmod> 2021-10-28 18:36:18.890205 </lastmod>
	</url><url>
		<loc> https://geoconnex.us/cuahsi/his/Mazar_River_Project/wq872 </loc>
		<lastmod> 2021-10-28 18:36:18.890219 </lastmod>
	</url><url>
		<loc> https://geoconnex.us/cuahsi/his/Mazar_River_Project/wq874 </loc>
		<lastmod> 2021-10-28 18:36:18.890233 </lastmod>
	</url><url>
		<loc> https://geoconnex.us/cuahsi/his/Mazar_River_Project/wq880 </loc>
		<lastmod> 2021-10-28 18:36:18.890247 </lastmod>
	</url><url>
		<loc> https://geoconnex.us/cuahsi/his/Mazar_River_Project/wq925 </loc>
		<lastmod> 2021-10-28 18:36:18.890261 </lastmod>
	</url><url>
		<loc> https://geoconnex.us/cuahsi/his/Mazar_River_Project/wq926 </loc>
		<lastmod> 2021-10-28 18:36:18.890274 </lastmod>
	</url><url>
		<loc> https://geoconnex.us/cuahsi/his/Mazar_River_Project/wq927 </loc>
		<lastmod> 2021-10-28 18:36:18.890288 </lastmod>
	</url><url>
		<loc> https://geoconnex.us/cuahsi/his/Mazar_River_Project/wq928 </loc>
		<lastmod> 2021-10-28 18:36:18.890302 </lastmod>
	</url><url>
		<loc> https://geoconnex.us/cuahsi/his/Mazar_River_Project/wq929 </loc>
		<lastmod> 2021-10-28 18:36:18.890315 </lastmod>
	</url><url>
		<loc> https://geoconnex.us/cuahsi/his/Mazar_River_Project/wq1155 </loc>
		<lastmod> 2021-10-28 18:36:18.890329 </lastmod>
	</url><url>
		<loc> https://geoconnex.us/cuahsi/his/Mazar_River_Project/wq1159 </loc>
		<lastmod> 2021-10-28 18:36:18.890344 </lastmod>
	</url><url>
		<loc> https://geoconnex.us/cuahsi/his/Mazar_River_Project/wq1167 </loc>
		<lastmod> 2021-10-28 18:36:18.890358 </lastmod>
	</url><url>
		<loc> https://geoconnex.us/cuahsi/his/Mazar_River_Project/wq1169 </loc>
		<lastmod> 2021-10-28 18:36:18.890372 </lastmod>
	</url><url>
		<loc> https://geoconnex.us/cuahsi/his/Mazar_River_Project/wq1170 </loc>
		<lastmod> 2021-10-28 18:36:18.890387 </lastmod>
	</url><url>
		<loc> https://geoconnex.us/cuahsi/his/Mazar_River_Project/wq1171 </loc>
		<lastmod> 2021-10-28 18:36:18.890401 </lastmod>
	</url><url>
		<loc> https://geoconnex.us/cuahsi/his/Mazar_River_Project/wq1174 </loc>
		<lastmod> 2021-10-28 18:36:18.890414 </lastmod>
	</url><url>
		<loc> https://geoconnex.us/cuahsi/his/Mazar_River_Project/wq1201 </loc>
		<lastmod> 2021-10-28 18:36:18.890428 </lastmod>
	</url><url>
		<loc> https://geoconnex.us/cuahsi/his/Mazar_River_Project/wq1202 </loc>
		<lastmod> 2021-10-28 18:36:18.890442 </lastmod>
	</url><url>
		<loc> https://geoconnex.us/cuahsi/his/Mazar_River_Project/wq1203 </loc>
		<lastmod> 2021-10-28 18:36:18.890456 </lastmod>
	</url><url>
		<loc> https://geoconnex.us/cuahsi/his/Mazar_River_Project/wq1204 </loc>
		<lastmod> 2021-10-28 18:36:18.890470 </lastmod>
	</url><url>
		<loc> https://geoconnex.us/cuahsi/his/Mazar_River_Project/wq1205 </loc>
		<lastmod> 2021-10-28 18:36:18.890484 </lastmod>
	</url><url>
		<loc> https://geoconnex.us/cuahsi/his/Mazar_River_Project/wq1206 </loc>
		<lastmod> 2021-10-28 18:36:18.890498 </lastmod>
	</url><url>
		<loc> https://geoconnex.us/cuahsi/his/Mazar_River_Project/wq1207 </loc>
		<lastmod> 2021-10-28 18:36:18.890511 </lastmod>
	</url><url>
		<loc> https://geoconnex.us/cuahsi/his/Mazar_River_Project/wq1208 </loc>
		<lastmod> 2021-10-28 18:36:18.890525 </lastmod>
	</url><url>
		<loc> https://geoconnex.us/cuahsi/his/Mazar_River_Project/wq1211 </loc>
		<lastmod> 2021-10-28 18:36:18.890539 </lastmod>
	</url><url>
		<loc> https://geoconnex.us/cuahsi/his/Mazar_River_Project/wq1220 </loc>
		<lastmod> 2021-10-28 18:36:18.890552 </lastmod>
	</url><url>
		<loc> https://geoconnex.us/cuahsi/his/Mazar_River_Project/wq1245 </loc>
		<lastmod> 2021-10-28 18:36:18.890566 </lastmod>
	</url><url>
		<loc> https://geoconnex.us/cuahsi/his/Mazar_River_Project/wq1256 </loc>
		<lastmod> 2021-10-28 18:36:18.890580 </lastmod>
	</url><url>
		<loc> https://geoconnex.us/cuahsi/his/Mazar_River_Project/wq1259 </loc>
		<lastmod> 2021-10-28 18:36:18.890593 </lastmod>
	</url><url>
		<loc> https://geoconnex.us/cuahsi/his/Mazar_River_Project/wq1260 </loc>
		<lastmod> 2021-10-28 18:36:18.890607 </lastmod>
	</url><url>
		<loc> https://geoconnex.us/cuahsi/his/Mazar_River_Project/wq1262 </loc>
		<lastmod> 2021-10-28 18:36:18.890621 </lastmod>
	</url><url>
		<loc> https://geoconnex.us/cuahsi/his/Mazar_River_Project/wq1263 </loc>
		<lastmod> 2021-10-28 18:36:18.890635 </lastmod>
	</url><url>
		<loc> https://geoconnex.us/cuahsi/his/Mazar_River_Project/wq1282 </loc>
		<lastmod> 2021-10-28 18:36:18.890685 </lastmod>
	</url><url>
		<loc> https://geoconnex.us/cuahsi/his/Mazar_River_Project/wq1296 </loc>
		<lastmod> 2021-10-28 18:36:18.890699 </lastmod>
	</url><url>
		<loc> https://geoconnex.us/cuahsi/his/Mazar_River_Project/wq1312 </loc>
		<lastmod> 2021-10-28 18:36:18.890713 </lastmod>
	</url><url>
		<loc> https://geoconnex.us/cuahsi/his/Mazar_River_Project/wq1328 </loc>
		<lastmod> 2021-10-28 18:36:18.890727 </lastmod>
	</url><url>
		<loc> https://geoconnex.us/cuahsi/his/Mazar_River_Project/wq1329 </loc>
		<lastmod> 2021-10-28 18:36:18.890741 </lastmod>
	</url><url>
		<loc> https://geoconnex.us/cuahsi/his/Mazar_River_Project/wq1331 </loc>
		<lastmod> 2021-10-28 18:36:18.890755 </lastmod>
	</url><url>
		<loc> https://geoconnex.us/cuahsi/his/Mazar_River_Project/wq1332 </loc>
		<lastmod> 2021-10-28 18:36:18.890770 </lastmod>
	</url><url>
		<loc> https://geoconnex.us/cuahsi/his/Mazar_River_Project/wq1333 </loc>
		<lastmod> 2021-10-28 18:36:18.890783 </lastmod>
	</url><url>
		<loc> https://geoconnex.us/cuahsi/his/Mazar_River_Project/wq1334 </loc>
		<lastmod> 2021-10-28 18:36:18.890797 </lastmod>
	</url><url>
		<loc> https://geoconnex.us/cuahsi/his/Mazar_River_Project/wq1335 </loc>
		<lastmod> 2021-10-28 18:36:18.890811 </lastmod>
	</url><url>
		<loc> https://geoconnex.us/cuahsi/his/Mazar_River_Project/wq1353 </loc>
		<lastmod> 2021-10-28 18:36:18.890825 </lastmod>
	</url><url>
		<loc> https://geoconnex.us/cuahsi/his/Mazar_River_Project/wq1354 </loc>
		<lastmod> 2021-10-28 18:36:18.890838 </lastmod>
	</url><url>
		<loc> https://geoconnex.us/cuahsi/his/Mazar_River_Project/wq1355 </loc>
		<lastmod> 2021-10-28 18:36:18.890852 </lastmod>
	</url><url>
		<loc> https://geoconnex.us/cuahsi/his/Mazar_River_Project/wq1356 </loc>
		<lastmod> 2021-10-28 18:36:18.890866 </lastmod>
	</url><url>
		<loc> https://geoconnex.us/cuahsi/his/Mazar_River_Project/wq1357 </loc>
		<lastmod> 2021-10-28 18:36:18.890879 </lastmod>
	</url><url>
		<loc> https://geoconnex.us/cuahsi/his/Mazar_River_Project/wq1358 </loc>
		<lastmod> 2021-10-28 18:36:18.890893 </lastmod>
	</url><url>
		<loc> https://geoconnex.us/cuahsi/his/Mazar_River_Project/wq1359 </loc>
		<lastmod> 2021-10-28 18:36:18.890907 </lastmod>
	</url><url>
		<loc> https://geoconnex.us/cuahsi/his/Mazar_River_Project/wq1361 </loc>
		<lastmod> 2021-10-28 18:36:18.890921 </lastmod>
	</url><url>
		<loc> https://geoconnex.us/cuahsi/his/Mazar_River_Project/wq1362 </loc>
		<lastmod> 2021-10-28 18:36:18.890934 </lastmod>
	</url><url>
		<loc> https://geoconnex.us/cuahsi/his/Mazar_River_Project/wq1363 </loc>
		<lastmod> 2021-10-28 18:36:18.890948 </lastmod>
	</url><url>
		<loc> https://geoconnex.us/cuahsi/his/Mazar_River_Project/wq1367 </loc>
		<lastmod> 2021-10-28 18:36:18.890962 </lastmod>
	</url><url>
		<loc> https://geoconnex.us/cuahsi/his/Mazar_River_Project/wq1375 </loc>
		<lastmod> 2021-10-28 18:36:18.890976 </lastmod>
	</url><url>
		<loc> https://geoconnex.us/cuahsi/his/Mazar_River_Project/wq1398 </loc>
		<lastmod> 2021-10-28 18:36:18.890989 </lastmod>
	</url><url>
		<loc> https://geoconnex.us/cuahsi/his/Mazar_River_Project/wq1400 </loc>
		<lastmod> 2021-10-28 18:36:18.891003 </lastmod>
	</url><url>
		<loc> https://geoconnex.us/cuahsi/his/Mazar_River_Project/wq1445 </loc>
		<lastmod> 2021-10-28 18:36:18.891016 </lastmod>
	</url><url>
		<loc> https://geoconnex.us/cuahsi/his/Mazar_River_Project/wq1447 </loc>
		<lastmod> 2021-10-28 18:36:18.891030 </lastmod>
	</url><url>
		<loc> https://geoconnex.us/cuahsi/his/Mazar_River_Project/wq1456 </loc>
		<lastmod> 2021-10-28 18:36:18.891044 </lastmod>
	</url><url>
		<loc> https://geoconnex.us/cuahsi/his/Mazar_River_Project/wq1460 </loc>
		<lastmod> 2021-10-28 18:36:18.891057 </lastmod>
	</url><url>
		<loc> https://geoconnex.us/cuahsi/his/Mazar_River_Project/wq1462 </loc>
		<lastmod> 2021-10-28 18:36:18.891072 </lastmod>
	</url><url>
		<loc> https://geoconnex.us/cuahsi/his/Mazar_River_Project/wq1472 </loc>
		<lastmod> 2021-10-28 18:36:18.891085 </lastmod>
	</url><url>
		<loc> https://geoconnex.us/cuahsi/his/Mazar_River_Project/wq1473 </loc>
		<lastmod> 2021-10-28 18:36:18.891099 </lastmod>
	</url><url>
		<loc> https://geoconnex.us/cuahsi/his/Mazar_River_Project/wq1490 </loc>
		<lastmod> 2021-10-28 18:36:18.891112 </lastmod>
	</url><url>
		<loc> https://geoconnex.us/cuahsi/his/Mazar_River_Project/wq1492 </loc>
		<lastmod> 2021-10-28 18:36:18.891126 </lastmod>
	</url><url>
		<loc> https://geoconnex.us/cuahsi/his/Mazar_River_Project/wq1494 </loc>
		<lastmod> 2021-10-28 18:36:18.891140 </lastmod>
	</url><url>
		<loc> https://geoconnex.us/cuahsi/his/Mazar_River_Project/wq1495 </loc>
		<lastmod> 2021-10-28 18:36:18.891153 </lastmod>
	</url><url>
		<loc> https://geoconnex.us/cuahsi/his/Mazar_River_Project/wq1531 </loc>
		<lastmod> 2021-10-28 18:36:18.891167 </lastmod>
	</url><url>
		<loc> https://geoconnex.us/cuahsi/his/Mazar_River_Project/wq1532 </loc>
		<lastmod> 2021-10-28 18:36:18.891181 </lastmod>
	</url><url>
		<loc> https://geoconnex.us/cuahsi/his/Mazar_River_Project/wq1533 </loc>
		<lastmod> 2021-10-28 18:36:18.891195 </lastmod>
	</url><url>
		<loc> https://geoconnex.us/cuahsi/his/Mazar_River_Project/wq1534 </loc>
		<lastmod> 2021-10-28 18:36:18.891208 </lastmod>
	</url><url>
		<loc> https://geoconnex.us/cuahsi/his/Mazar_River_Project/wq1535 </loc>
		<lastmod> 2021-10-28 18:36:18.891222 </lastmod>
	</url><url>
		<loc> https://geoconnex.us/cuahsi/his/Mazar_River_Project/wq1536 </loc>
		<lastmod> 2021-10-28 18:36:18.891236 </lastmod>
	</url><url>
		<loc> https://geoconnex.us/cuahsi/his/Mazar_River_Project/wq1537 </loc>
		<lastmod> 2021-10-28 18:36:18.891250 </lastmod>
	</url><url>
		<loc> https://geoconnex.us/cuahsi/his/Mazar_River_Project/wq1538 </loc>
		<lastmod> 2021-10-28 18:36:18.891264 </lastmod>
	</url><url>
		<loc> https://geoconnex.us/cuahsi/his/Mazar_River_Project/wq1539 </loc>
		<lastmod> 2021-10-28 18:36:18.891277 </lastmod>
	</url><url>
		<loc> https://geoconnex.us/cuahsi/his/Mazar_River_Project/wq1540 </loc>
		<lastmod> 2021-10-28 18:36:18.891291 </lastmod>
	</url><url>
		<loc> https://geoconnex.us/cuahsi/his/Mazar_River_Project/wq1541 </loc>
		<lastmod> 2021-10-28 18:36:18.891304 </lastmod>
	</url><url>
		<loc> https://geoconnex.us/cuahsi/his/Mazar_River_Project/wq1542 </loc>
		<lastmod> 2021-10-28 18:36:18.891318 </lastmod>
	</url><url>
		<loc> https://geoconnex.us/cuahsi/his/Mazar_River_Project/wq1543 </loc>
		<lastmod> 2021-10-28 18:36:18.891332 </lastmod>
	</url><url>
		<loc> https://geoconnex.us/cuahsi/his/Mazar_River_Project/wq1544 </loc>
		<lastmod> 2021-10-28 18:36:18.891345 </lastmod>
	</url><url>
		<loc> https://geoconnex.us/cuahsi/his/Mazar_River_Project/wq1588 </loc>
		<lastmod> 2021-10-28 18:36:18.891359 </lastmod>
	</url><url>
		<loc> https://geoconnex.us/cuahsi/his/Mazar_River_Project/wq1591 </loc>
		<lastmod> 2021-10-28 18:36:18.891373 </lastmod>
	</url><url>
		<loc> https://geoconnex.us/cuahsi/his/Mazar_River_Project/wq1595 </loc>
		<lastmod> 2021-10-28 18:36:18.891386 </lastmod>
	</url><url>
		<loc> https://geoconnex.us/cuahsi/his/Mazar_River_Project/wq1596 </loc>
		<lastmod> 2021-10-28 18:36:18.891400 </lastmod>
	</url><url>
		<loc> https://geoconnex.us/cuahsi/his/Mazar_River_Project/wq1629 </loc>
		<lastmod> 2021-10-28 18:36:18.891413 </lastmod>
	</url><url>
		<loc> https://geoconnex.us/cuahsi/his/Mazar_River_Project/wq1657 </loc>
		<lastmod> 2021-10-28 18:36:18.891427 </lastmod>
	</url><url>
		<loc> https://geoconnex.us/cuahsi/his/Mazar_River_Project/wq1671 </loc>
		<lastmod> 2021-10-28 18:36:18.891441 </lastmod>
	</url><url>
		<loc> https://geoconnex.us/cuahsi/his/Mazar_River_Project/wq1681 </loc>
		<lastmod> 2021-10-28 18:36:18.891455 </lastmod>
	</url><url>
		<loc> https://geoconnex.us/cuahsi/his/Mazar_River_Project/wq1749 </loc>
		<lastmod> 2021-10-28 18:36:18.891469 </lastmod>
	</url><url>
		<loc> https://geoconnex.us/cuahsi/his/Mazar_River_Project/wq1750 </loc>
		<lastmod> 2021-10-28 18:36:18.891483 </lastmod>
	</url><url>
		<loc> https://geoconnex.us/cuahsi/his/Mazar_River_Project/wq1751 </loc>
		<lastmod> 2021-10-28 18:36:18.891496 </lastmod>
	</url><url>
		<loc> https://geoconnex.us/cuahsi/his/Mazar_River_Project/wq1752 </loc>
		<lastmod> 2021-10-28 18:36:18.891510 </lastmod>
	</url><url>
		<loc> https://geoconnex.us/cuahsi/his/Mazar_River_Project/wq1753 </loc>
		<lastmod> 2021-10-28 18:36:18.891524 </lastmod>
	</url><url>
		<loc> https://geoconnex.us/cuahsi/his/Mazar_River_Project/wq1759 </loc>
		<lastmod> 2021-10-28 18:36:18.891538 </lastmod>
	</url><url>
		<loc> https://geoconnex.us/cuahsi/his/Mazar_River_Project/wq1761 </loc>
		<lastmod> 2021-10-28 18:36:18.891551 </lastmod>
	</url><url>
		<loc> https://geoconnex.us/cuahsi/his/Mazar_River_Project/wq1763 </loc>
		<lastmod> 2021-10-28 18:36:18.891566 </lastmod>
	</url><url>
		<loc> https://geoconnex.us/cuahsi/his/Mazar_River_Project/wq1850 </loc>
		<lastmod> 2021-10-28 18:36:18.891580 </lastmod>
	</url><url>
		<loc> https://geoconnex.us/cuahsi/his/Mazar_River_Project/wq1852 </loc>
		<lastmod> 2021-10-28 18:36:18.891593 </lastmod>
	</url><url>
		<loc> https://geoconnex.us/cuahsi/his/Mazar_River_Project/wq1853 </loc>
		<lastmod> 2021-10-28 18:36:18.891607 </lastmod>
	</url><url>
		<loc> https://geoconnex.us/cuahsi/his/Mazar_River_Project/wq1858 </loc>
		<lastmod> 2021-10-28 18:36:18.891621 </lastmod>
	</url><url>
		<loc> https://geoconnex.us/cuahsi/his/Mazar_River_Project/wq1864 </loc>
		<lastmod> 2021-10-28 18:36:18.891635 </lastmod>
	</url><url>
		<loc> https://geoconnex.us/cuahsi/his/Mazar_River_Project/wq1873 </loc>
		<lastmod> 2021-10-28 18:36:18.891648 </lastmod>
	</url><url>
		<loc> https://geoconnex.us/cuahsi/his/Mazar_River_Project/wq1875 </loc>
		<lastmod> 2021-10-28 18:36:18.891662 </lastmod>
	</url><url>
		<loc> https://geoconnex.us/cuahsi/his/Mazar_River_Project/wq1877 </loc>
		<lastmod> 2021-10-28 18:36:18.891676 </lastmod>
	</url><url>
		<loc> https://geoconnex.us/cuahsi/his/Mazar_River_Project/wq1878 </loc>
		<lastmod> 2021-10-28 18:36:18.891690 </lastmod>
	</url><url>
		<loc> https://geoconnex.us/cuahsi/his/Mazar_River_Project/wq1879 </loc>
		<lastmod> 2021-10-28 18:36:18.891703 </lastmod>
	</url><url>
		<loc> https://geoconnex.us/cuahsi/his/Mazar_River_Project/wq2029 </loc>
		<lastmod> 2021-10-28 18:36:18.891717 </lastmod>
	</url><url>
		<loc> https://geoconnex.us/cuahsi/his/Mazar_River_Project/wq2032 </loc>
		<lastmod> 2021-10-28 18:36:18.891731 </lastmod>
	</url><url>
		<loc> https://geoconnex.us/cuahsi/his/Mazar_River_Project/wq2033 </loc>
		<lastmod> 2021-10-28 18:36:18.891744 </lastmod>
	</url><url>
		<loc> https://geoconnex.us/cuahsi/his/Mazar_River_Project/wq2101 </loc>
		<lastmod> 2021-10-28 18:36:18.891758 </lastmod>
	</url><url>
		<loc> https://geoconnex.us/cuahsi/his/Mazar_River_Project/wq2121 </loc>
		<lastmod> 2021-10-28 18:36:18.891771 </lastmod>
	</url><url>
		<loc> https://geoconnex.us/cuahsi/his/Mazar_River_Project/wq2123 </loc>
		<lastmod> 2021-10-28 18:36:18.891785 </lastmod>
	</url><url>
		<loc> https://geoconnex.us/cuahsi/his/Mazar_River_Project/wq2124 </loc>
		<lastmod> 2021-10-28 18:36:18.891799 </lastmod>
	</url><url>
		<loc> https://geoconnex.us/cuahsi/his/Mazar_River_Project/wq2125 </loc>
		<lastmod> 2021-10-28 18:36:18.891813 </lastmod>
	</url><url>
		<loc> https://geoconnex.us/cuahsi/his/Mazar_River_Project/wq2126 </loc>
		<lastmod> 2021-10-28 18:36:18.891827 </lastmod>
	</url><url>
		<loc> https://geoconnex.us/cuahsi/his/Mazar_River_Project/wq2129 </loc>
		<lastmod> 2021-10-28 18:36:18.891841 </lastmod>
	</url><url>
		<loc> https://geoconnex.us/cuahsi/his/Mazar_River_Project/wq2132 </loc>
		<lastmod> 2021-10-28 18:36:18.891855 </lastmod>
	</url><url>
		<loc> https://geoconnex.us/cuahsi/his/Mazar_River_Project/wq2133 </loc>
		<lastmod> 2021-10-28 18:36:18.891869 </lastmod>
	</url><url>
		<loc> https://geoconnex.us/cuahsi/his/Mazar_River_Project/wq2135 </loc>
		<lastmod> 2021-10-28 18:36:18.891883 </lastmod>
	</url><url>
		<loc> https://geoconnex.us/cuahsi/his/Mazar_River_Project/wq2136 </loc>
		<lastmod> 2021-10-28 18:36:18.891897 </lastmod>
	</url><url>
		<loc> https://geoconnex.us/cuahsi/his/Mazar_River_Project/wq2256 </loc>
		<lastmod> 2021-10-28 18:36:18.891911 </lastmod>
	</url><url>
		<loc> https://geoconnex.us/cuahsi/his/Mazar_River_Project/wq2257 </loc>
		<lastmod> 2021-10-28 18:36:18.891924 </lastmod>
	</url><url>
		<loc> https://geoconnex.us/cuahsi/his/Mazar_River_Project/wq2371 </loc>
		<lastmod> 2021-10-28 18:36:18.891939 </lastmod>
	</url><url>
		<loc> https://geoconnex.us/cuahsi/his/Mazar_River_Project/wq2775 </loc>
		<lastmod> 2021-10-28 18:36:18.891953 </lastmod>
	</url><url>
		<loc> https://geoconnex.us/cuahsi/his/Mazar_River_Project/wq2780 </loc>
		<lastmod> 2021-10-28 18:36:18.891966 </lastmod>
	</url><url>
		<loc> https://geoconnex.us/cuahsi/his/Mazar_River_Project/wq2781 </loc>
		<lastmod> 2021-10-28 18:36:18.891980 </lastmod>
	</url><url>
		<loc> https://geoconnex.us/cuahsi/his/Mazar_River_Project/wq2782 </loc>
		<lastmod> 2021-10-28 18:36:18.891994 </lastmod>
	</url></ns0:urlset>