<?xml version="1.0" encoding="UTF-8"?>
<backup xmlns="urn:csiro:xmlns:pidsvc:backup:1.0">
  <mapping>
    <path>/cuahsi/his/Logan_River_GAMUT/LR_WaterLab_AA</path>
    <type>1:1</type>
    <description>Logan River at the Utah Water Research Laboratory west bridge</description>
    <creator>acastronova@cuahsi.org</creator>
    <action>
      <type>303</type>
      <name>location</name>
      <value>http://selfie.cuahsi.org/Logan%20River%20GAMUT/LR_WaterLab_AA</value>
    </action>
    <conditions>
      <condition>
        <type>QueryString</type>
        <match>f?=.*</match>
        <actions>
          <action>
            <type>303</type>
            <name>location</name>
            <value>http://selfie.cuahsi.org/Logan%20River%20GAMUT/LR_WaterLab_AA?f=${C:f:1}</value>
          </action>
        </actions>
      </condition>
    </conditions>
  </mapping>
  <mapping>
    <path>/cuahsi/his/Logan_River_GAMUT/LR_Mendon_AA</path>
    <type>1:1</type>
    <description>Logan River at Mendon Road (600 South)</description>
    <creator>acastronova@cuahsi.org</creator>
    <action>
      <type>303</type>
      <name>location</name>
      <value>http://selfie.cuahsi.org/Logan%20River%20GAMUT/LR_Mendon_AA</value>
    </action>
    <conditions>
      <condition>
        <type>QueryString</type>
        <match>f?=.*</match>
        <actions>
          <action>
            <type>303</type>
            <name>location</name>
            <value>http://selfie.cuahsi.org/Logan%20River%20GAMUT/LR_Mendon_AA?f=${C:f:1}</value>
          </action>
        </actions>
      </condition>
    </conditions>
  </mapping>
  <mapping>
    <path>/cuahsi/his/Logan_River_GAMUT/LR_MainStreet_BA</path>
    <type>1:1</type>
    <description>Logan River at Main Street (Highway 89/91) Bridge</description>
    <creator>acastronova@cuahsi.org</creator>
    <action>
      <type>303</type>
      <name>location</name>
      <value>http://selfie.cuahsi.org/Logan%20River%20GAMUT/LR_MainStreet_BA</value>
    </action>
    <conditions>
      <condition>
        <type>QueryString</type>
        <match>f?=.*</match>
        <actions>
          <action>
            <type>303</type>
            <name>location</name>
            <value>http://selfie.cuahsi.org/Logan%20River%20GAMUT/LR_MainStreet_BA?f=${C:f:1}</value>
          </action>
        </actions>
      </condition>
    </conditions>
  </mapping>
  <mapping>
    <path>/cuahsi/his/Logan_River_GAMUT/LR_TWDEF_C</path>
    <type>1:1</type>
    <description>Climate Station at TW Daniels Experimental Forest</description>
    <creator>acastronova@cuahsi.org</creator>
    <action>
      <type>303</type>
      <name>location</name>
      <value>http://selfie.cuahsi.org/Logan%20River%20GAMUT/LR_TWDEF_C</value>
    </action>
    <conditions>
      <condition>
        <type>QueryString</type>
        <match>f?=.*</match>
        <actions>
          <action>
            <type>303</type>
            <name>location</name>
            <value>http://selfie.cuahsi.org/Logan%20River%20GAMUT/LR_TWDEF_C?f=${C:f:1}</value>
          </action>
        </actions>
      </condition>
    </conditions>
  </mapping>
  <mapping>
    <path>/cuahsi/his/Logan_River_GAMUT/LR_GC_C</path>
    <type>1:1</type>
    <description>Climate Station at Logan River Golf Course</description>
    <creator>acastronova@cuahsi.org</creator>
    <action>
      <type>303</type>
      <name>location</name>
      <value>http://selfie.cuahsi.org/Logan%20River%20GAMUT/LR_GC_C</value>
    </action>
    <conditions>
      <condition>
        <type>QueryString</type>
        <match>f?=.*</match>
        <actions>
          <action>
            <type>303</type>
            <name>location</name>
            <value>http://selfie.cuahsi.org/Logan%20River%20GAMUT/LR_GC_C?f=${C:f:1}</value>
          </action>
        </actions>
      </condition>
    </conditions>
  </mapping>
  <mapping>
    <path>/cuahsi/his/Logan_River_GAMUT/LR_Wilkins_R</path>
    <type>1:1</type>
    <description>Wilkins Repeater</description>
    <creator>acastronova@cuahsi.org</creator>
    <action>
      <type>303</type>
      <name>location</name>
      <value>http://selfie.cuahsi.org/Logan%20River%20GAMUT/LR_Wilkins_R</value>
    </action>
    <conditions>
      <condition>
        <type>QueryString</type>
        <match>f?=.*</match>
        <actions>
          <action>
            <type>303</type>
            <name>location</name>
            <value>http://selfie.cuahsi.org/Logan%20River%20GAMUT/LR_Wilkins_R?f=${C:f:1}</value>
          </action>
        </actions>
      </condition>
    </conditions>
  </mapping>
  <mapping>
    <path>/cuahsi/his/Logan_River_GAMUT/LR_TG_C</path>
    <type>1:1</type>
    <description>Climate Station at Tony Grove</description>
    <creator>acastronova@cuahsi.org</creator>
    <action>
      <type>303</type>
      <name>location</name>
      <value>http://selfie.cuahsi.org/Logan%20River%20GAMUT/LR_TG_C</value>
    </action>
    <conditions>
      <condition>
        <type>QueryString</type>
        <match>f?=.*</match>
        <actions>
          <action>
            <type>303</type>
            <name>location</name>
            <value>http://selfie.cuahsi.org/Logan%20River%20GAMUT/LR_TG_C?f=${C:f:1}</value>
          </action>
        </actions>
      </condition>
    </conditions>
  </mapping>
  <mapping>
    <path>/cuahsi/his/Logan_River_GAMUT/LR_FB_C</path>
    <type>1:1</type>
    <description>Climate Station at Franklin Basin</description>
    <creator>acastronova@cuahsi.org</creator>
    <action>
      <type>303</type>
      <name>location</name>
      <value>http://selfie.cuahsi.org/Logan%20River%20GAMUT/LR_FB_C</value>
    </action>
    <conditions>
      <condition>
        <type>QueryString</type>
        <match>f?=.*</match>
        <actions>
          <action>
            <type>303</type>
            <name>location</name>
            <value>http://selfie.cuahsi.org/Logan%20River%20GAMUT/LR_FB_C?f=${C:f:1}</value>
          </action>
        </actions>
      </condition>
    </conditions>
  </mapping>
  <mapping>
    <path>/cuahsi/his/Logan_River_GAMUT/LR_TG_BA</path>
    <type>1:1</type>
    <description>Logan River near Tony Grove</description>
    <creator>acastronova@cuahsi.org</creator>
    <action>
      <type>303</type>
      <name>location</name>
      <value>http://selfie.cuahsi.org/Logan%20River%20GAMUT/LR_TG_BA</value>
    </action>
    <conditions>
      <condition>
        <type>QueryString</type>
        <match>f?=.*</match>
        <actions>
          <action>
            <type>303</type>
            <name>location</name>
            <value>http://selfie.cuahsi.org/Logan%20River%20GAMUT/LR_TG_BA?f=${C:f:1}</value>
          </action>
        </actions>
      </condition>
    </conditions>
  </mapping>
  <mapping>
    <path>/cuahsi/his/Logan_River_GAMUT/LR_FB_BA</path>
    <type>1:1</type>
    <description>Logan River near Franklin Basin</description>
    <creator>acastronova@cuahsi.org</creator>
    <action>
      <type>303</type>
      <name>location</name>
      <value>http://selfie.cuahsi.org/Logan%20River%20GAMUT/LR_FB_BA</value>
    </action>
    <conditions>
      <condition>
        <type>QueryString</type>
        <match>f?=.*</match>
        <actions>
          <action>
            <type>303</type>
            <name>location</name>
            <value>http://selfie.cuahsi.org/Logan%20River%20GAMUT/LR_FB_BA?f=${C:f:1}</value>
          </action>
        </actions>
      </condition>
    </conditions>
  </mapping>
  <mapping>
    <path>/cuahsi/his/Logan_River_GAMUT/LR_RH_SD</path>
    <type>1:1</type>
    <description>River Heights Bridge Storm Drain</description>
    <creator>acastronova@cuahsi.org</creator>
    <action>
      <type>303</type>
      <name>location</name>
      <value>http://selfie.cuahsi.org/Logan%20River%20GAMUT/LR_RH_SD</value>
    </action>
    <conditions>
      <condition>
        <type>QueryString</type>
        <match>f?=.*</match>
        <actions>
          <action>
            <type>303</type>
            <name>location</name>
            <value>http://selfie.cuahsi.org/Logan%20River%20GAMUT/LR_RH_SD?f=${C:f:1}</value>
          </action>
        </actions>
      </condition>
    </conditions>
  </mapping>
  <mapping>
    <path>/cuahsi/his/Logan_River_GAMUT/LR_SC_SD</path>
    <type>1:1</type>
    <description>Spring Creek Storm Drain (Decomissioned)</description>
    <creator>acastronova@cuahsi.org</creator>
    <action>
      <type>303</type>
      <name>location</name>
      <value>http://selfie.cuahsi.org/Logan%20River%20GAMUT/LR_SC_SD</value>
    </action>
    <conditions>
      <condition>
        <type>QueryString</type>
        <match>f?=.*</match>
        <actions>
          <action>
            <type>303</type>
            <name>location</name>
            <value>http://selfie.cuahsi.org/Logan%20River%20GAMUT/LR_SC_SD?f=${C:f:1}</value>
          </action>
        </actions>
      </condition>
    </conditions>
  </mapping>
  <mapping>
    <path>/cuahsi/his/Logan_River_GAMUT/BSF_CONF_BA</path>
    <type>1:1</type>
    <description>Blacksmith Fork above confluence with Logan River</description>
    <creator>acastronova@cuahsi.org</creator>
    <action>
      <type>303</type>
      <name>location</name>
      <value>http://selfie.cuahsi.org/Logan%20River%20GAMUT/BSF_CONF_BA</value>
    </action>
    <conditions>
      <condition>
        <type>QueryString</type>
        <match>f?=.*</match>
        <actions>
          <action>
            <type>303</type>
            <name>location</name>
            <value>http://selfie.cuahsi.org/Logan%20River%20GAMUT/BSF_CONF_BA?f=${C:f:1}</value>
          </action>
        </actions>
      </condition>
    </conditions>
  </mapping>
  <mapping>
    <path>/cuahsi/his/Logan_River_GAMUT/NWF_1600N_CNL</path>
    <type>1:1</type>
    <description>Northwest Field Canal at 1600 North</description>
    <creator>acastronova@cuahsi.org</creator>
    <action>
      <type>303</type>
      <name>location</name>
      <value>http://selfie.cuahsi.org/Logan%20River%20GAMUT/NWF_1600N_CNL</value>
    </action>
    <conditions>
      <condition>
        <type>QueryString</type>
        <match>f?=.*</match>
        <actions>
          <action>
            <type>303</type>
            <name>location</name>
            <value>http://selfie.cuahsi.org/Logan%20River%20GAMUT/NWF_1600N_CNL?f=${C:f:1}</value>
          </action>
        </actions>
      </condition>
    </conditions>
  </mapping>
  <mapping>
    <path>/cuahsi/his/Logan_River_GAMUT/SLB_Pump_CNL</path>
    <type>1:1</type>
    <description>South Logan Benson Canal at Airport Rd Pumping Station</description>
    <creator>acastronova@cuahsi.org</creator>
    <action>
      <type>303</type>
      <name>location</name>
      <value>http://selfie.cuahsi.org/Logan%20River%20GAMUT/SLB_Pump_CNL</value>
    </action>
    <conditions>
      <condition>
        <type>QueryString</type>
        <match>f?=.*</match>
        <actions>
          <action>
            <type>303</type>
            <name>location</name>
            <value>http://selfie.cuahsi.org/Logan%20River%20GAMUT/SLB_Pump_CNL?f=${C:f:1}</value>
          </action>
        </actions>
      </condition>
    </conditions>
  </mapping>
  <mapping>
    <path>/cuahsi/his/Logan_River_GAMUT/SC_CONF_A</path>
    <type>1:1</type>
    <description>Spring Creek above confluence with Logan River</description>
    <creator>acastronova@cuahsi.org</creator>
    <action>
      <type>303</type>
      <name>location</name>
      <value>http://selfie.cuahsi.org/Logan%20River%20GAMUT/SC_CONF_A</value>
    </action>
    <conditions>
      <condition>
        <type>QueryString</type>
        <match>f?=.*</match>
        <actions>
          <action>
            <type>303</type>
            <name>location</name>
            <value>http://selfie.cuahsi.org/Logan%20River%20GAMUT/SC_CONF_A?f=${C:f:1}</value>
          </action>
        </actions>
      </condition>
    </conditions>
  </mapping>
  <mapping>
    <path>/cuahsi/his/Logan_River_GAMUT/LR_WCB_A</path>
    <type>1:1</type>
    <description>Logan River at Wood Camp Bridge</description>
    <creator>acastronova@cuahsi.org</creator>
    <action>
      <type>303</type>
      <name>location</name>
      <value>http://selfie.cuahsi.org/Logan%20River%20GAMUT/LR_WCB_A</value>
    </action>
    <conditions>
      <condition>
        <type>QueryString</type>
        <match>f?=.*</match>
        <actions>
          <action>
            <type>303</type>
            <name>location</name>
            <value>http://selfie.cuahsi.org/Logan%20River%20GAMUT/LR_WCB_A?f=${C:f:1}</value>
          </action>
        </actions>
      </condition>
    </conditions>
  </mapping>
  <mapping>
    <path>/cuahsi/his/Logan_River_GAMUT/LR_GCB_A</path>
    <type>1:1</type>
    <description>Logan River at Guinavah Campground Bridge</description>
    <creator>acastronova@cuahsi.org</creator>
    <action>
      <type>303</type>
      <name>location</name>
      <value>http://selfie.cuahsi.org/Logan%20River%20GAMUT/LR_GCB_A</value>
    </action>
    <conditions>
      <condition>
        <type>QueryString</type>
        <match>f?=.*</match>
        <actions>
          <action>
            <type>303</type>
            <name>location</name>
            <value>http://selfie.cuahsi.org/Logan%20River%20GAMUT/LR_GCB_A?f=${C:f:1}</value>
          </action>
        </actions>
      </condition>
    </conditions>
  </mapping>
</backup>
